feagi_bytes/__init__.py
feagi_bytes/constants.py
feagi_bytes/serialization.py
feagi_bytes/translator.py
feagi_bytes/utils.py
tests/__init__.py
tests/test_serialization.py
tests/test_translator.py
feagi_bytes-0.1.0.dist-info/METADATA
feagi_bytes-0.1.0.dist-info/WHEEL
feagi_bytes-0.1.0.dist-info/top_level.txt
feagi_bytes-0.1.0.dist-info/RECORD
