Metadata-Version: 2.4
Name: feagi_bytes
Version: 0.1.0
Summary: Binary serialization for FEAGI protocols
Home-page: https://github.com/feagi/feagi_bytes
Author: Neuraville Inc.
Author-email: feagi@neuraville.com
Project-URL: Bug Tracker, https://github.com/feagi/feagi_bytes/issues
Classifier: Programming Language :: Python :: 3
Classifier: License :: OSI Approved :: Apache Software License
Classifier: Operating System :: OS Independent
Requires-Python: >=3.8
Requires-Dist: numpy>=1.20.0
Dynamic: author
Dynamic: author-email
Dynamic: classifier
Dynamic: description
Dynamic: description-content-type
Dynamic: home-page
Dynamic: project-url
Dynamic: requires-dist
Dynamic: requires-python
Dynamic: summary
